[
  {
    "url": "https://blog.avas.space/clean-girl-klein-dogwhistle/",
    "title": "the girly wellness aesthetic as a white supremacist dog whistle",
    "author": "https://blog.avas.space",
    "toasts": 26,
    "first_seen": "2026-06-17T14:14:51.789Z",
    "last_updated": "2026-06-17T16:20:09.684Z",
    "published": "2026-06-17T11:00Z"
  },
  {
    "url": "https://unturnedhovel.bearblog.dev/the-spiritual-healing-of-oracular-play/",
    "title": "The Spiritual Healing of Oracular Play",
    "author": "https://unturnedhovel.bearblog.dev",
    "toasts": 7,
    "first_seen": "2026-06-17T16:20:09.684Z",
    "last_updated": "2026-06-17T16:20:09.684Z",
    "published": "2026-06-17T14:45Z"
  },
  {
    "url": "https://sakshamwrites.bearblog.dev/the-learners-high/",
    "title": "The Learner's High",
    "author": "https://sakshamwrites.bearblog.dev",
    "toasts": 7,
    "first_seen": "2026-06-17T16:20:09.684Z",
    "last_updated": "2026-06-17T16:20:09.684Z",
    "published": "2026-06-17T03:09Z"
  },
  {
    "url": "https://explicatingelle.bearblog.dev/ai-use-case-conundrum/",
    "title": "AI Use Case Conundrum",
    "author": "https://explicatingelle.bearblog.dev",
    "toasts": 6,
    "first_seen": "2026-06-17T16:20:09.684Z",
    "last_updated": "2026-06-17T16:20:09.684Z",
    "published": "2026-06-17T13:56Z"
  },
  {
    "url": "https://blog.lauramichet.com/i-installed-a-giant-antenna-on-my-mesh-radio/",
    "title": "I installed a giant antenna on my mesh radio",
    "author": "https://blog.lauramichet.com",
    "toasts": 6,
    "first_seen": "2026-06-17T16:20:09.684Z",
    "last_updated": "2026-06-17T16:20:09.684Z",
    "published": "2026-06-17T00:45Z"
  },
  {
    "url": "https://idraluna-archives.bearblog.dev/dungeon-glyphs/",
    "title": "Dungeon Glyphs",
    "author": "https://idraluna-archives.bearblog.dev",
    "toasts": 6,
    "first_seen": "2026-06-17T16:20:09.684Z",
    "last_updated": "2026-06-17T16:20:09.684Z",
    "published": "2026-06-17T00:05Z"
  }
]
