[
  {
    "url": "https://pseudosingleton.com/becoming-even-more-of-a-hater/",
    "title": "Becoming even more of a Hater",
    "author": "https://pseudosingleton.com",
    "toasts": 14,
    "first_seen": "2026-05-05T05:09:16.972Z",
    "last_updated": "2026-05-05T08:53:05.595Z",
    "published": "2026-05-05T02:39Z"
  },
  {
    "url": "https://kadennewton.com/learning-how-to-email/",
    "title": "Learning how to Email",
    "author": "https://kadennewton.com",
    "toasts": 15,
    "first_seen": "2026-05-05T07:43:55.624Z",
    "last_updated": "2026-05-06T07:04:28.267Z",
    "published": "2026-05-05T02:04Z"
  },
  {
    "url": "https://next.kennyqin.com/notification-schedules/",
    "title": "Notification Schedules Are Your Responsibility",
    "author": "https://next.kennyqin.com",
    "toasts": 14,
    "first_seen": "2026-05-05T08:53:05.595Z",
    "last_updated": "2026-05-06T05:11:56.352Z",
    "published": "2026-05-05T06:18Z"
  },
  {
    "url": "https://silvers.bearblog.dev/quick-life-update/",
    "title": "Quick life update",
    "author": "https://silvers.bearblog.dev",
    "toasts": 10,
    "first_seen": "2026-05-05T08:53:05.595Z",
    "last_updated": "2026-05-05T15:42:53.267Z",
    "published": "2026-05-05T05:55Z"
  },
  {
    "url": "https://receipts.bearblog.dev/tantrums-are-best-ignored/",
    "title": "tantrums are best ignored",
    "author": "https://receipts.bearblog.dev",
    "toasts": 7,
    "first_seen": "2026-05-05T11:33:18.603Z",
    "last_updated": "2026-05-05T15:42:53.267Z",
    "published": "2026-05-05T05:57Z"
  },
  {
    "url": "https://blog.bearroll.dev/april-stats/",
    "title": "bearroll.dev - April Stats from Bear Blog trending",
    "author": "https://blog.bearroll.dev",
    "toasts": 11,
    "first_seen": "2026-05-05T13:58:55.374Z",
    "last_updated": "2026-05-05T18:39:06.688Z",
    "published": "2026-05-05T11:59Z"
  },
  {
    "url": "https://woolgathering.bearblog.dev/learning-to-talk-about-things-i-like/",
    "title": "learning to talk about things i like",
    "author": "https://woolgathering.bearblog.dev",
    "toasts": 17,
    "first_seen": "2026-05-05T15:42:53.267Z",
    "last_updated": "2026-05-06T07:04:28.267Z",
    "published": "2026-05-05T11:40Z"
  },
  {
    "url": "https://garnet.bearblog.dev/things-inside-other-things/",
    "title": "things inside other things",
    "author": "https://garnet.bearblog.dev",
    "toasts": 11,
    "first_seen": "2026-05-05T17:38:34.288Z",
    "last_updated": "2026-05-06T03:14:52.899Z",
    "published": "2026-05-05T06:01Z"
  },
  {
    "url": "https://chupacabra.bearblog.dev/should-i-delete-my-amazon-account/",
    "title": "Should I delete my Amazon account?",
    "author": "https://chupacabra.bearblog.dev",
    "toasts": 12,
    "first_seen": "2026-05-05T18:39:06.688Z",
    "last_updated": "2026-05-06T07:04:28.267Z",
    "published": "2026-05-05T11:01Z"
  },
  {
    "url": "https://blog.sulimans.space/superior-alts/",
    "title": "institutionally managed open source alternatives that don’t suck",
    "author": "https://blog.sulimans.space",
    "toasts": 8,
    "first_seen": "2026-05-05T18:39:06.688Z",
    "last_updated": "2026-05-05T20:30:42.876Z",
    "published": "2026-05-05T13:55Z"
  },
  {
    "url": "https://musings101.bearblog.dev/bear-blog-carnival-i-love-my-cinnamon-disc-golf/",
    "title": "Bear Blog Carnival: I love my Cinnamon (Disc Golf)",
    "author": "https://musings101.bearblog.dev",
    "toasts": 7,
    "first_seen": "2026-05-05T18:39:06.688Z",
    "last_updated": "2026-05-06T01:40:44.243Z",
    "published": "2026-05-05T13:49Z"
  },
  {
    "url": "https://chas.quest/tough-days-are-ok/",
    "title": "Tough Days are OK",
    "author": "https://chas.quest",
    "toasts": 6,
    "first_seen": "2026-05-05T18:39:06.688Z",
    "last_updated": "2026-05-05T18:39:06.688Z",
    "published": "2026-05-05T13:48Z"
  },
  {
    "url": "https://winther.sysctl.dk/nostalgia-for-calvin-and-hobbes/",
    "title": "Nostalgia for Calvin and Hobbes",
    "author": "https://winther.sysctl.dk",
    "toasts": 7,
    "first_seen": "2026-05-05T21:27:20.415Z",
    "last_updated": "2026-05-06T05:11:56.352Z",
    "published": "2026-05-05T17:45Z"
  },
  {
    "url": "https://mossbed.bearblog.dev/abandoning-the-algorithm/",
    "title": "abandoning the algorithm",
    "author": "https://mossbed.bearblog.dev",
    "toasts": 11,
    "first_seen": "2026-05-06T01:40:44.243Z",
    "last_updated": "2026-05-06T07:04:28.267Z",
    "published": "2026-05-05T23:36Z"
  },
  {
    "url": "https://imperfect.bearblog.dev/preserve-your-artifacts/",
    "title": "preserve your artifacts",
    "author": "https://imperfect.bearblog.dev",
    "toasts": 6,
    "first_seen": "2026-05-06T03:14:52.899Z",
    "last_updated": "2026-05-06T03:14:52.899Z",
    "published": "2026-05-05T19:30Z"
  }
]
