[
  {
    "url": "https://moodywarlock.net/a-group-of-ghouls-and-ai-exhaustion/",
    "title": "A group of ghouls and ai exhaustion",
    "author": "https://moodywarlock.net",
    "toasts": 52,
    "first_seen": "2026-05-23T08:48:16.912Z",
    "last_updated": "2026-05-23T17:26:12.101Z",
    "published": "2026-05-23T07:03Z"
  },
  {
    "url": "https://pinewind.bearblog.dev/a-silly-thing-that-i-do/",
    "title": "a silly thing that I do",
    "author": "https://pinewind.bearblog.dev",
    "toasts": 32,
    "first_seen": "2026-05-23T08:48:16.912Z",
    "last_updated": "2026-05-23T17:26:12.101Z",
    "published": "2026-05-23T05:00Z"
  },
  {
    "url": "https://skryblans.com/vibe-blogging/",
    "title": "vibe blogging",
    "author": "https://skryblans.com",
    "toasts": 36,
    "first_seen": "2026-05-23T11:30:06.590Z",
    "last_updated": "2026-05-23T17:26:12.101Z",
    "published": "2026-05-23T08:29Z"
  },
  {
    "url": "https://stellardecay.com/first-cattiversary/",
    "title": "First Cattiversary!",
    "author": "https://stellardecay.com",
    "toasts": 34,
    "first_seen": "2026-05-23T11:30:06.590Z",
    "last_updated": "2026-05-23T17:26:12.101Z",
    "published": "2026-05-23T10:09Z"
  },
  {
    "url": "https://monolog.xyz/popular-bear-blog-posts/",
    "title": "popular posts on bear blog",
    "author": "https://monolog.xyz",
    "toasts": 21,
    "first_seen": "2026-05-23T13:35:41.916Z",
    "last_updated": "2026-05-23T17:26:12.101Z",
    "published": "2026-05-23T11:24Z"
  },
  {
    "url": "https://blog.avas.space/brussels/",
    "title": "my experience in brussels",
    "author": "https://blog.avas.space",
    "toasts": 33,
    "first_seen": "2026-05-23T13:35:41.916Z",
    "last_updated": "2026-05-23T17:26:12.101Z",
    "published": "2026-05-23T10:33Z"
  },
  {
    "url": "https://robertbirming.com/prettier-palettes-previews/",
    "title": "Prettier palettes with previews",
    "author": "https://robertbirming.com",
    "toasts": 44,
    "first_seen": "2026-05-23T13:35:41.916Z",
    "last_updated": "2026-05-23T17:26:12.101Z",
    "published": "2026-05-23T12:34Z"
  },
  {
    "url": "https://www.natemeyvis.com/you-really-dont-have-to-use-substack/",
    "title": "You really don't have to use Substack",
    "author": "https://www.natemeyvis.com",
    "toasts": 33,
    "first_seen": "2026-05-23T14:36:53.923Z",
    "last_updated": "2026-05-23T17:26:12.101Z",
    "published": "2026-05-23T12:55Z"
  },
  {
    "url": "https://robertbirming.com/unpopular-posts-bear-blog/",
    "title": "Unpopular posts on Bear blog",
    "author": "https://robertbirming.com",
    "toasts": 32,
    "first_seen": "2026-05-23T14:36:53.923Z",
    "last_updated": "2026-05-23T17:26:12.101Z",
    "published": "2026-05-23T13:38Z"
  },
  {
    "url": "https://robynbirdblog.bearblog.dev/you-dont-have-to-film-yourself-and-share-what-you-hate-on-social-platform/",
    "title": "You don't have to film yourself and share what you hate on social platform",
    "author": "https://robynbirdblog.bearblog.dev",
    "toasts": 29,
    "first_seen": "2026-05-23T14:36:53.923Z",
    "last_updated": "2026-05-23T17:26:12.101Z",
    "published": "2026-05-23T10:38Z"
  },
  {
    "url": "https://radarambles.bearblog.dev/being-trending-gave-me-stage-fright/",
    "title": "Being trending gave me stage fright",
    "author": "https://radarambles.bearblog.dev",
    "toasts": 9,
    "first_seen": "2026-05-23T14:36:53.923Z",
    "last_updated": "2026-05-23T15:29:04.475Z",
    "published": "2026-05-23T12:54Z"
  },
  {
    "url": "https://technically-good.ca/newsletter/009-2026-05-23/",
    "title": "💌 Newsletter #009 - Social Media Alternatives (Good!), Bill C-22 (Not So Good!), and The End of Google Search as We Know It",
    "author": "https://technically-good.ca",
    "toasts": 24,
    "first_seen": "2026-05-23T15:29:04.475Z",
    "last_updated": "2026-05-23T17:26:12.101Z",
    "published": "2026-05-23T14:12Z"
  },
  {
    "url": "https://emersonwick.page/free-zines-online/",
    "title": "Free Zines Online",
    "author": "https://emersonwick.page",
    "toasts": 8,
    "first_seen": "2026-05-23T15:29:04.475Z",
    "last_updated": "2026-05-23T15:29:04.475Z",
    "published": "2026-05-23T13:05Z"
  },
  {
    "url": "https://forkingmad.blog/no-trial-or-monthly-version-no-thanks/",
    "title": "No Trial or Monthly version = No Thanks",
    "author": "https://forkingmad.blog",
    "toasts": 10,
    "first_seen": "2026-05-23T16:26:18.476Z",
    "last_updated": "2026-05-23T16:26:18.476Z",
    "published": "2026-05-23T14:43Z"
  },
  {
    "url": "https://topopa.bearblog.dev/i-went-to-an-event-about-moths/",
    "title": "I went to an event about moths",
    "author": "https://topopa.bearblog.dev",
    "toasts": 10,
    "first_seen": "2026-05-23T16:26:18.476Z",
    "last_updated": "2026-05-23T17:26:12.101Z",
    "published": "2026-05-23T14:49Z"
  }
]
