[
  {
    "url": "https://skuka.online/giving-myself-permission-to-not-think-of-millenials-or-gen-z-or-boomers/",
    "title": "giving myself permission to not think of millenials or gen z (or boomers)",
    "author": "https://skuka.online",
    "toasts": 10,
    "first_seen": "2026-05-15T15:47:06.293Z",
    "last_updated": "2026-05-15T16:41:00.869Z",
    "published": "2026-05-15T13:13Z"
  },
  {
    "url": "https://trueself.bearblog.dev/if-you-like-someones-blog-you-should-probably-tell-them/",
    "title": "If you like someone’s blog, you should probably tell them",
    "author": "https://trueself.bearblog.dev",
    "toasts": 12,
    "first_seen": "2026-05-15T16:41:00.869Z",
    "last_updated": "2026-05-15T18:40:08.864Z",
    "published": "2026-05-15T16:22Z"
  },
  {
    "url": "https://justaqueerbookblog.bearblog.dev/boo-pinterest/",
    "title": "I Hate AI More Than I Miss Pinterest",
    "author": "https://justaqueerbookblog.bearblog.dev",
    "toasts": 10,
    "first_seen": "2026-05-15T18:40:08.864Z",
    "last_updated": "2026-05-15T18:40:08.864Z",
    "published": "2026-05-15T17:00Z"
  },
  {
    "url": "https://tala.bearblog.dev/writing-poetry-exploring-creativity-letting-loose-pt-ii/",
    "title": "writing poetry, exploring creativity & letting loose, pt ii",
    "author": "https://tala.bearblog.dev",
    "toasts": 8,
    "first_seen": "2026-05-15T18:40:08.864Z",
    "last_updated": "2026-05-15T18:40:08.864Z",
    "published": "2026-05-15T14:52Z"
  },
  {
    "url": "https://skryblans.com/todays-dilemma/",
    "title": "today's dilemma",
    "author": "https://skryblans.com",
    "toasts": 8,
    "first_seen": "2026-05-15T18:40:08.864Z",
    "last_updated": "2026-05-15T18:40:08.864Z",
    "published": "2026-05-15T11:14Z"
  }
]
